[
    {
        "id": "1",
        "name": "Пицца Маргарита 30 СМ",
        "price": "190",
        "img": "assets/img/cotalog/1.png",
		"desc": "Сыр Моцарелла, соус томатный",
		"kkal": "1054",
		"ghir": "52г",
		"prot": "30г",
		"yglev": "141г"
    },
    {
        "id": "2",
        "name": "Пицца Барбекю 30 СМ",
        "price": "280",
        "img": "assets/img/cotalog/2.png",
		"desc": "Куриная грудка, сыр моцарелла, соус барбекю, шампиньоны, лук тушеный, ананас, зелень",
		"kkal": "1116",
		"ghir": "59г",
		"prot": "26г",
		"yglev": "159г"
    },
    {
        "id": "3",
        "name": "Пицца пять сыров 30 СМ",
        "price": "230",
        "img": "assets/img/cotalog/3.png",
		"desc": "Томатный соус, сыр копченый, моцарелла, гауда, чеддер, пармезан, тимьян, мед",
		"kkal": "1440",
		"ghir": "52г",
		"prot": "85г",
		"yglev": "117г"
    },
    {
        "id": "4",
        "name": "Пицца дуэт 30 СМ",
        "price": "330",
        "img": "assets/img/cotalog/4.png",
		"desc": "4",
		"kkal": "1462",
		"ghir": "56г",
		"prot": "55г",
		"yglev": "200г"
    },
    {
        "id": "5",
        "name": "Пицца с опятами 30 СМ",
        "price": "310",
        "img": "assets/img/cotalog/5.png",
		"desc": "Томатный соус, соус верона, моцарелла, помидоры, кура филе, бекон, шампиньоны, пармезан, орегано",
		"kkal": "1462",
		"ghir": "56г",
		"prot": "55г",
		"yglev": "200г"
    },
	 {
        "id": "6",
        "name": "Пицца четыре сыра 30 СМ ",
        "price": "290",
        "img": "assets/img/cotalog/6.png",
		 "desc": "Сыр Моцарелла, сыр Чеддер, сыр Дор блю, сыр Пармезан, соус Верона, мед.",
		 "kkal": "1380",
		"ghir": "44г",
		"prot": "77г",
		"yglev": "129г"
    }
	
]